svllm/__about__.py
svllm/__init__.py
svllm/base.py
svllm/client.py
svllm/examples.py
svllm/helpers.py
svllm/main.py
svllm/protocol.py
svllm/routes.py
svllm/server.py
svllm/services.py
svllm/openai/__init__.py
svllm/openai/chat.py
svllm/openai/complete.py
svllm/openai/embed.py
svllm/openai/helpers.py
svllm/openai/models.py
svllm/openai/protocol.py
svllm/openai/routes.py
svllm-0.2.3.dist-info/METADATA
svllm-0.2.3.dist-info/WHEEL
svllm-0.2.3.dist-info/entry_points.txt
svllm-0.2.3.dist-info/licenses/LICENSE
svllm-0.2.3.dist-info/RECORD
