Metadata-Version: 2.4
Name: svllm
Version: 0.2.3
Summary: serve your llm
Project-URL: Documentation, https://github.com/conwnet/svllm#readme
Project-URL: Issues, https://github.com/conwnet/svllm/issues
Project-URL: Source, https://github.com/conwnet/svllm
Author-email: netcon <netcon@live.com>
License-Expression: MIT
License-File: LICENSE
Classifier: Programming Language :: Python :: 3
Classifier: Programming Language :: Python :: 3.9
Classifier: Programming Language :: Python :: 3.10
Classifier: Programming Language :: Python :: 3.11
Classifier: Programming Language :: Python :: 3.12
Classifier: Programming Language :: Python :: 3.13
Requires-Python: >=3.9
Requires-Dist: fastapi
Requires-Dist: httpx
Requires-Dist: pydantic<3,>=2.0.0
Requires-Dist: shortuuid
Requires-Dist: termcolor
Requires-Dist: uvicorn
